mem_store/__init__.py
mem_store/_mem_store.py
mem_store-0.2.1.dist-info/LICENSE
mem_store-0.2.1.dist-info/METADATA
mem_store-0.2.1.dist-info/WHEEL
mem_store-0.2.1.dist-info/RECORD
